README.md
setup.py
generators/Generator.py
generators/__init__.py
generators/__main__.py
generators/__test__.py
generators/all_subslices.py
generators/all_substrings.py
generators/alternator.py
generators/apply_to_last.py
generators/average.py
generators/chain.py
generators/chunk_on.py
generators/chunks.py
generators/consume.py
generators/counter.py
generators/early_warning.py
generators/every_other.py
generators/first.py
generators/fork.py
generators/inline_tools.py
generators/itemgetter.py
generators/iter_csv.py
generators/iter_kv.py
generators/iterable.py
generators/just.py
generators/last.py
generators/loop.py
generators/map.py
generators/map_parallel.py
generators/multi_ops.py
generators/peekable.py
generators/performance_tools.py
generators/read.py
generators/remember.py
generators/repeater.py
generators/reverse.py
generators/side_task.py
generators/skip.py
generators/skip_errors.py
generators/skip_first.py
generators/skip_last.py
generators/split.py
generators/started.py
generators/switch.py
generators/tee.py
generators/timed_pipe.py
generators/timer.py
generators/total.py
generators/unfork.py
generators/uniq.py
generators/window.py
generators.egg-info/PKG-INFO
generators.egg-info/SOURCES.txt
generators.egg-info/dependency_links.txt
generators.egg-info/requires.txt
generators.egg-info/top_level.txt
generators.egg-info/zip-safe
generators/tests/__init__.py
generators/tests/test_apply_to_last.py
generators/tests/test_chunk_on.py
generators/tests/test_chunks.py
generators/tests/test_map_parallel.py
generators/tests/test_skip_errors.py
generators/tests/test_switch.py