Metadata-Version: 1.1
Name: generators
Version: 2020.2.4
Summary: a high performance pipeline processor written in python
Home-page: https://github.com/CodyKochmann/generators
Author: Cody Kochmann
Author-email: kochmanncody@gmail.com
License: UNKNOWN
Download-URL: https://github.com/CodyKochmann/generators/tarball/2020.2.4
Keywords: generators,iter,itertools,combinations,pipe,pipeline,performance,fast,chain,iterate,gen,Generator
Platform: UNKNOWN
